hdf_dq_framework/__init__.py
hdf_dq_framework/config_examples.py
hdf_dq_framework/dq_framework.py
hdf_dq_framework/rule_processor.py
hdf_dq_framework-1.0.2.dist-info/METADATA
hdf_dq_framework-1.0.2.dist-info/WHEEL
hdf_dq_framework-1.0.2.dist-info/RECORD
