Metadata-Version: 2.3
Name: hdf-dq-framework
Version: 1.0.2
Summary: HDF Data Quality Framework for PySpark DataFrames using Great Expectations
Home-page: https://github.com/your-org/hdf-data-pipeline
License: MIT
Keywords: data-quality,pyspark,great-expectations,dataframe,validation
Author: HDF Data Pipeline Team nengkhoiba.chungkham@iqvia.com
Requires-Python: >=3.8,<4.0
Classifier: Development Status :: 3 - Alpha
Classifier: Intended Audience :: Developers
Classifier: License :: OSI Approved :: MIT License
Classifier: Operating System :: OS Independent
Classifier: Programming Language :: Python :: 3
Classifier: Programming Language :: Python :: 3.8
Classifier: Programming Language :: Python :: 3.9
Classifier: Programming Language :: Python :: 3.10
Classifier: Programming Language :: Python :: 3.11
Classifier: Programming Language :: Python :: 3.12
Classifier: Programming Language :: Python :: 3.13
Classifier: Topic :: Database
Classifier: Topic :: Scientific/Engineering :: Information Analysis
Classifier: Topic :: Software Development :: Libraries :: Python Modules
Provides-Extra: enhanced
Requires-Dist: great-expectations (>=0.15.0,<0.16.0)
Requires-Dist: numpy (>=1.20.0,<2.0.0) ; extra == "enhanced"
Requires-Dist: pandas (>=1.3.0,<2.0.0) ; extra == "enhanced"
Requires-Dist: pyspark (>=3.0.0,<4.0.0)
Requires-Dist: typing-extensions (>=4.0.0,<5.0.0)
Project-URL: Documentation, https://github.com/your-org/hdf-data-pipeline
Project-URL: Repository, https://github.com/your-org/hdf-data-pipeline
